CATK/__init__.py
CATK/location.py
CATK/name.py
CATK/pleiad.py
CATK/pleiades_wrangler.py
CATK/topos_tool_kit.py
CATK/utils.py
CATK/data/ToposTextGazetteer.jsonld
CATK/data/classical_place_refs.csv
CATK/data/pleiades-places-latest.json.gz
CATK/data/topos_data.csv
CATK/data/topos_text_htms/topos_text_gazeteer.jsonld
catk-0.0.1.dist-info/METADATA
catk-0.0.1.dist-info/WHEEL
catk-0.0.1.dist-info/licenses/LICENSE
catk-0.0.1.dist-info/RECORD
